__init__.py
amarium/__init__.py
amarium/checks.py
amarium/checks.pyi
amarium/csv_utils.py
amarium/csv_utils.pyi
amarium/encryption.py
amarium/encryption.pyi
amarium/utils.py
amarium/utils.pyi
amarium-0.2.18.dist-info/METADATA
amarium-0.2.18.dist-info/WHEEL
amarium-0.2.18.dist-info/top_level.txt
amarium-0.2.18.dist-info/RECORD
